[{"id":1727206,"title":"Аккурганский район"},{"id":1727212,"title":"Ахангаранский район"},{"id":1727220,"title":"Бекабадский район"},{"id":1727224,"title":"Бостанлыкский район"},{"id":1727228,"title":"Букинский район"},{"id":1727233,"title":"Куйичирчикский район"},{"id":1727237,"title":"Зангиатинский район"},{"id":1727239,"title":"Юкоричирчикский район"},{"id":1727248,"title":"Кибрайский район"},{"id":1727249,"title":"Паркентский район"},{"id":1727250,"title":"Пскентский район"},{"id":1727253,"title":"Уртачирчикский район"},{"id":1727256,"title":"Чиназский район"},{"id":1727259,"title":"Янгиюльский район"},{"id":1727265,"title":"Ташкентский район"},{"id":1727401,"title":"г. Нурафшан"},{"id":1727404,"title":"г. Алмалык"},{"id":1727407,"title":"г. Ангрен"},{"id":1727413,"title":"г. Бекабад"},{"id":1727415,"title":"г. Ахангаран"},{"id":1727419,"title":"г. Чирчик"},{"id":1727424,"title":"г. Янгиюль"}]