[{"id":1710207,"title":"G`uzor tumani"},{"id":1710212,"title":"Dehqonobod tumani"},{"id":1710220,"title":"Qamashi tumani"},{"id":1710224,"title":"Qarshi tumani"},{"id":1710229,"title":"Koson tumani"},{"id":1710232,"title":"Kitob tumani"},{"id":1710233,"title":"Mirishkor tumani"},{"id":1710234,"title":"Muborak tumani"},{"id":1710235,"title":"Nishon tumani"},{"id":1710237,"title":"Kasbi tumani"},{"id":1710240,"title":"Ko‘kdala tumani"},{"id":1710242,"title":"Chiroqchi tumani"},{"id":1710245,"title":"Shahrisabz tumani"},{"id":1710250,"title":"Yakkabog` tumani"},{"id":1710401,"title":"Qarshi shahri"},{"id":1710405,"title":"Shahrisabz shahri"}]