[{"id":1714401365450010,"title":"Bog‘ МФЙ"},{"id":1714401365450022,"title":"Davlatobod МФЙ"},{"id":1714401365450089,"title":"Elobod МФЙ"},{"id":1714401365250018,"title":"Gulobod МФЙ"},{"id":1714401365150020,"title":"Gulshan МФЙ"},{"id":1714401365150777,"title":"Ijodkor МФЙ"},{"id":1714401365250030,"title":"Irvadon МФЙ"},{"id":1714401365350781,"title":"Istiqlol МФЙ"},{"id":1714401365350050,"title":"Mustaqillik МФЙ"},{"id":1714401365350052,"title":"Navbahor МФЙ"},{"id":1714401365150053,"title":"Navro‘z МФЙ"},{"id":1714401365150055,"title":"Nurobod МФЙ"},{"id":1714401365450075,"title":"O‘rta G‘irvon МФЙ"},{"id":1714401365250076,"title":"O‘rta Rovuston МФЙ"},{"id":1714401365150063,"title":"Orzu МФЙ"},{"id":1714401365350065,"title":"Porloq МФЙ"},{"id":1714401365450037,"title":"Quyi G‘irvon МФЙ"},{"id":1714401365250038,"title":"Quyi Rovuston МФЙ"},{"id":1714401365450087,"title":"Shishaki МФЙ"},{"id":1714401365150780,"title":"Tadbirkor МФЙ"},{"id":1714401365250073,"title":"To‘quvchi МФЙ"},{"id":1714401365350074,"title":"Umid МФЙ"},{"id":1714401365350081,"title":"Xalqlar do‘stligi МФЙ"},{"id":1714401365350097,"title":"Yangi tong МФЙ"},{"id":1714401365150422,"title":"Yelxon МФЙ"},{"id":1714401365150031,"title":"Yuksalish МФЙ"},{"id":1714401365450090,"title":"Yuqori G‘irvon МФЙ"},{"id":1714401365250091,"title":"Yuqori Rovuston МФЙ"}]