[{"id":1708201450012,"title":"Бахтли МФЙ"},{"id":1708201350008,"title":"Бобур МФЙ"},{"id":1708201450013,"title":"Бўстон МФЙ"},{"id":1708201150004,"title":"Гулбаҳор МФЙ"},{"id":1708201350011,"title":"Ғолиблар ШФЙ"},{"id":1708201350009,"title":"Ғофур Ғулом МФЙ"},{"id":1708201150003,"title":"Дўстлик МФЙ"},{"id":1708201250007,"title":"Зарафшон МФЙ"},{"id":1708201350010,"title":"Олтин Водий МФЙ"},{"id":1708201150001,"title":"Тинчлик МФЙ"},{"id":1708201250006,"title":"Чинобод МФЙ"},{"id":1708201150002,"title":"Чўлқувар МФЙ"},{"id":1708201250005,"title":"Янгибўстон МФЙ"}]